hangman/__init__.py
hangman/drawings.py
hangman/hangman.py
hangman_package-1.0.2.dist-info/LICENSE
hangman_package-1.0.2.dist-info/METADATA
hangman_package-1.0.2.dist-info/WHEEL
hangman_package-1.0.2.dist-info/top_level.txt
hangman_package-1.0.2.dist-info/RECORD
