Metadata-Version: 2.1
Name: hangman-package
Version: 1.0.2
Summary: A package to play a custom hangman game
Author-email: Vinicius Koji Enari <viniciusenari@gmail.com>
Project-URL: Homepage, https://github.com/viniciusenari/hangman-package
Classifier: Programming Language :: Python :: 3
Classifier: License :: OSI Approved :: MIT License
Classifier: Operating System :: OS Independent
Requires-Python: >=3.8
License-File: LICENSE
